Metadata-Version: 1.0
Name: python-vote-core
Version: 20120423.0
Summary: An implementation of various election methods, most notably the Schulze Method and Schulze STV.
Home-page: https://github.com/bradbeattie/python-vote-core
Author: Brad Beattie
Author-email: bradbeattie@gmail com
License: GPLv3
Keywords: library election
Platform: UNKNOWN
Classifier: Development Status :: 5 - Production/Stable
Classifier: License :: OSI Approved :: GNU General Public License (GPL)
Classifier: Programming Language :: Python
Classifier: Programming Language :: Python :: 2.7
Classifier: Topic :: Scientific/Engineering :: Mathematics
